CHANGES.rst
MANIFEST.in
README.rst
requirements.txt
setup.cfg
setup.py
template_to_pdf/__init__.py
template_to_pdf.egg-info/PKG-INFO
template_to_pdf.egg-info/SOURCES.txt
template_to_pdf.egg-info/dependency_links.txt
template_to_pdf.egg-info/requires.txt
template_to_pdf.egg-info/top_level.txt