Metadata-Version: 1.1
Name: template-to-pdf
Version: 0.0.3
Summary: Tool for converting HTML templates to PDF
Home-page: https://github.com/olist/template_to_pdf
Author: Olist Developers
Author-email: developers@olist.com
License: UNKNOWN
Platform: UNKNOWN
Classifier: Development Status :: 4 - Beta
Classifier: Intended Audience :: Developers
Classifier: Natural Language :: English
Classifier: Programming Language :: Python :: 3
Classifier: Programming Language :: Python :: 3.6
Classifier: Programming Language :: Python :: 3.7
Classifier: Topic :: Software Development :: Libraries
Classifier: Topic :: Software Development :: Pre-processors
Classifier: Topic :: Software Development :: Testing
